barbara/__init__.py
barbara/cli.py
barbara/readers.py
barbara/utils.py
barbara/variables.py
barbara/writers.py
barbara-2.3.0.dist-info/entry_points.txt
barbara-2.3.0.dist-info/LICENSE
barbara-2.3.0.dist-info/WHEEL
barbara-2.3.0.dist-info/METADATA
barbara-2.3.0.dist-info/RECORD
