Metadata-Version: 2.1
Name: barbara
Version: 2.3.0
Summary: Environment variable management
License: GPL-3.0
Author: Matthew de Verteuil
Author-email: onceuponajooks@gmail.com
Requires-Python: >=3.7.0,<4.0.0
Classifier: Development Status :: 5 - Production/Stable
Classifier: Environment :: Console
Classifier: Intended Audience :: Developers
Classifier: Intended Audience :: System Administrators
Classifier: License :: OSI Approved :: GNU General Public License v3 (GPLv3)
Classifier: Operating System :: MacOS
Classifier: Operating System :: POSIX :: Linux
Classifier: Operating System :: Unix
Classifier: Programming Language :: Python :: 3
Classifier: Programming Language :: Python :: 3.7
Classifier: Topic :: Software Development
Classifier: Topic :: System
Classifier: Topic :: Terminals
Requires-Dist: click (>=7.0.0,<8.0.0)
Requires-Dist: poetry-version (>=0.1.3,<1.0.0)
Requires-Dist: python-dotenv (>=0.10.1,<1.0.0)
Requires-Dist: pyyaml (>=5.1.0,<6.0.0)
